{
  "users": [
    {
      "id": "9ef9",
      "firstname": "mayur",
      "email": "mayur@gmail.com",
      "city": "nagar",
      "phone": "9022847474",
      "gender": "male",
      "country": "India",
      "social": [
        "Linkedin",
        "whatsapp",
        "instagram"
      ]
    },
    {
      "id": "17e0",
      "firstname": "vaibhav",
      "password": "123456789",
      "email": "vaibhavs12@gmail.com",
      "city": "pune",
      "phone": "9837373171",
      "gender": "male",
      "country": "India",
      "social": [
        "Linkedin",
        "whatsapp"
      ]
    }
  ],

  "logos": [
    {
      "imageUrl": "https://www.fusion-institute.com/_next/image?url=%2Fimg%2FaicteLogo.png&w=256&q=75",
      "altText": "AICTE Logo"
    },
    {
      "imageUrl": "https://www.fusion-institute.com/_next/image?url=%2Fimg%2FisoLogo.png&w=256&q=75",
      "altText": "ISO Logo"
    }
  ],
  "cards1": [
    {
      "title": "Quality Assurance",
      "description": "Our certification ensures rigorous quality control and continuous improvement in our processes."
    },
    {
      "title": "Productivity and Efficiency",
      "description": "Maximizing productivity and efficiency through streamlined processes and innovative methods."
    },
    {
      "title": "Customer Satisfaction",
      "description": "Our commitment to quality and compliance ensures our customers receive the best possible experience."
    }
  ],
 


  "cards": [
    {
      "id": 1,
      "icon": "CheckCircleOutlineIcon",
      "title": "Updated Curriculum",
      "description": "Learn latest industry trends and technologies."
    },
    {
      "id": 2,
      "icon": "TrendingUpIcon",
      "title": "Structured Learning Path",
      "description": "Structured courses designed by experts in the field."
    },
    {
      "id": 3,
      "icon": "LaptopIcon",
      "title": "Hands-on Experience",
      "description": "Work on projects and real-world scenarios."
    }
  ], 


  "corporateTraining": {
    "heading": "What is Corporate Training?",
    "sections": [
      {
        "text": "We define training as partnering with students in a thought-provoking, challenging and creative process that inspires them to maximize their personal and professional potential."
      },
      {
        "text": "The process of training often unlocks previously untapped sources of imagination, productivity, and leadership quality of both students and trainers."
      },
      {
        "text": "We all have goals we want to reach, challenges we're striving to overcome, and times when we feel stuck. Partnering with a trainer can change your life, setting you on a path to greater personal and professional fulfillment."
      }
    ],
    "imageUrl": "https://www.fusion-institute.com/_next/image?url=%2Fimg%2F16433.jpg&w=1920&q=75"
  },


  "features": [
    {
      "icon": "PeopleIcon",
      "title": "Limited Seat Batches"
    },
    {
      "icon": "ComputerIcon",
      "title": "Trainer-Led Sessions"
    },
    {
      "icon": "DescriptionIcon",
      "title": "Effective Resume Building"
    },
    {
      "icon": "HandshakeIcon",
      "title": "Weekly Mock Interviews"
    },
    {
      "icon": "GroupsIcon",
      "title": "Building Leadership Skills"
    },
    {
      "icon": "WorkIcon",
      "title": "Creating Team Work Spirit"
    }
  ],

  "visionMission": {
    "vision": "To be the global leader in pioneering innovative software solutions for fusion energy, driving the world towards a sustainable and clean energy future.",
    "mission": "To advance the frontier of fusion energy through the development of groundbreaking software solutions, fostering collaboration, innovation, and sustainability.",
    "visionImage": "https://www.fusion-institute.com/_next/image?url=%2Fimg%2F891.jpg&w=640&q=75",
    "missionImage": "https://www.fusion-institute.com/_next/image?url=%2Fimg%2F10330.jpg&w=640&q=75"
  }
}
 


